.hgignore
AUTHORS
LICENSE
MANIFEST.in
setup.py
setuptools_hg-0.2-py2.6.egg
django_livesettings.egg-info/PKG-INFO
django_livesettings.egg-info/SOURCES.txt
django_livesettings.egg-info/dependency_links.txt
django_livesettings.egg-info/top_level.txt
docs/about.rst
docs/requirements.rst
livesettings/__init__.py
livesettings/forms.py
livesettings/functions.py
livesettings/models.py
livesettings/overrides.py
livesettings/signals.py
livesettings/tests.py
livesettings/urls.py
livesettings/utils.py
livesettings/values.py
livesettings/views.py
livesettings/locale/de/LC_MESSAGES/django.mo
livesettings/locale/de/LC_MESSAGES/django.po
livesettings/locale/en/LC_MESSAGES/django.mo
livesettings/locale/en/LC_MESSAGES/django.po
livesettings/locale/es/LC_MESSAGES/django.po
livesettings/locale/fr/LC_MESSAGES/django.mo
livesettings/locale/fr/LC_MESSAGES/django.po
livesettings/locale/he/LC_MESSAGES/django.mo
livesettings/locale/he/LC_MESSAGES/django.po
livesettings/locale/it/LC_MESSAGES/django.mo
livesettings/locale/it/LC_MESSAGES/django.po
livesettings/locale/ko/LC_MESSAGES/django.mo
livesettings/locale/ko/LC_MESSAGES/django.po
livesettings/locale/pl/LC_MESSAGES/django.mo
livesettings/locale/pl/LC_MESSAGES/django.po
livesettings/locale/pt_BR/LC_MESSAGES/django.mo
livesettings/locale/pt_BR/LC_MESSAGES/django.po
livesettings/locale/ru/LC_MESSAGES/django.mo
livesettings/locale/ru/LC_MESSAGES/django.po
livesettings/locale/sv/LC_MESSAGES/django.mo
livesettings/locale/sv/LC_MESSAGES/django.po
livesettings/locale/tr/LC_MESSAGES/django.mo
livesettings/locale/tr/LC_MESSAGES/django.po
livesettings/templates/livesettings/_admin_site_views.html
livesettings/templates/livesettings/group_settings.html
livesettings/templates/livesettings/site_settings.html
livesettings/templates/livesettings/text.txt
livesettings/templatetags/__init__.py
livesettings/templatetags/config_tags.py
tests/__init__.py
tests/manage.py
tests/settings.py
tests/urls.py
tests/localsite/__init__.py
tests/localsite/models.py