Metadata-Version: 1.0
Name: django-livesettings
Version: 1.4-7
Summary: livesettings
Home-page: http://bitbucket.org/bkroeze/django-livesettings/
Author: Bruce Kroeze
Author-email: bruce@ecomsmith.com
License: New BSD License
Platform: any
Classifier: Development Status :: 4 - Beta
Classifier: Environment :: Web Environment
Classifier: Intended Audience :: Developers
Classifier: License :: OSI Approved :: BSD License
Classifier: Operating System :: OS Independent
Classifier: Programming Language :: Python
Classifier: Framework :: Django
